hdlfs/__about__.py
hdlfs/__init__.py
hdlfs/hdlfs.py
hdlfs/hdlfs_copy.py
hdlfs/hdlfsystem.py
pyhdlfs-0.0.17.dist-info/METADATA
pyhdlfs-0.0.17.dist-info/WHEEL
pyhdlfs-0.0.17.dist-info/entry_points.txt
pyhdlfs-0.0.17.dist-info/RECORD
