Metadata-Version: 2.3
Name: pyhdlfs
Version: 0.0.17
Summary: Python wrapper to SAP HDLFS API
Project-URL: Homepage, https://github.tools.sap/hda-xpm-frontrunner/pyhdlfs
Author-email: Thorsten Hapke <thorsten.hapke@sap.com>
License-Expression: MIT
Classifier: License :: OSI Approved :: MIT License
Classifier: Operating System :: OS Independent
Classifier: Programming Language :: Python :: 3.12
Requires-Python: >=3.7
Requires-Dist: pyarrow
Requires-Dist: requests
Requires-Dist: rich
